drf_aggregation/__init__.py
drf_aggregation/aggregation.py
drf_aggregation/helpers.py
drf_aggregation/mixins.py
drf_aggregation/settings.py
drf_aggregation/types.py
drf_aggregation/utils.py
drf_aggregation/aggregations/__init__.py
drf_aggregation/aggregations/common.py
drf_aggregation/aggregations/percent.py
drf_aggregation/aggregations/percentile.py
drf_aggregation/filters/__init__.py
drf_aggregation/filters/column_index.py
drf_aggregation/filters/truncate_date.py
drf_aggregation-2.1.2.dist-info/licenses/LICENSE
drf_aggregation-2.1.2.dist-info/METADATA
drf_aggregation-2.1.2.dist-info/WHEEL
drf_aggregation-2.1.2.dist-info/top_level.txt
drf_aggregation-2.1.2.dist-info/RECORD
