Metadata-Version: 2.4
Name: drf_aggregation
Version: 2.1.2
Summary: Get DB aggregations using Django ORM
Author-email: Nikita Balobanov <kit-oz@ya.ru>
License: MIT License
Project-URL: Homepage, https://github.com/kit-oz/drf-aggregation
Keywords: django,aggregation,django-rest-framework,django-orm
Classifier: Development Status :: 4 - Beta
Classifier: Framework :: Django
Classifier: Intended Audience :: Developers
Classifier: License :: OSI Approved :: MIT License
Classifier: Operating System :: OS Independent
Classifier: Programming Language :: Python
Classifier: Programming Language :: Python :: 3
Requires-Python: >=3.8
License-File: LICENSE
Requires-Dist: django>=3.0.0
Provides-Extra: dev
Requires-Dist: djangorestframework~=3.12; extra == "dev"
Requires-Dist: drf-complex-filter~=1.0; extra == "dev"
Requires-Dist: parameterized~=0.7; extra == "dev"
Dynamic: license-file
